{"last_updated":1771027572060,"server":"FrostedSMP","players":[{"uuid":"507c43ac-b2fe-42c7-94d3-cb41b3c0d55b","username":"Webberzz","display_name":"Webberzz","is_online":false,"stats":{"total_playtime":4251,"kills":8,"deaths":0,"blocks_broken":2894,"blocks_placed":711,"level":51,"distance_traveled":680553.91,"items_crafted":0,"mobs_killed":1,"food_eaten":6}},{"uuid":"b0f05894-6a43-4fb7-ae8d-15873d4f2535","username":"Mehtsack","display_name":"Mehtsack","is_online":true,"stats":{"total_playtime":3626,"kills":2,"deaths":4,"blocks_broken":10162,"blocks_placed":1560,"level":45,"distance_traveled":290271.81,"items_crafted":110,"mobs_killed":122,"food_eaten":86}},{"uuid":"f132d52b-60d1-4f49-948a-6aba033963a8","username":"drift129","display_name":"drift129","is_online":false,"stats":{"total_playtime":1664,"kills":2,"deaths":13,"blocks_broken":652,"blocks_placed":311,"level":4,"distance_traveled":117583.34,"items_crafted":5,"mobs_killed":0,"food_eaten":1}},{"uuid":"bd1dfd29-a640-4a84-a5ca-514cdda521b7","username":"meat22proguns","display_name":"meat22proguns","is_online":true,"stats":{"total_playtime":988,"kills":0,"deaths":0,"blocks_broken":814,"blocks_placed":340,"level":45,"distance_traveled":99245.61,"items_crafted":34,"mobs_killed":23,"food_eaten":70}},{"uuid":"bee461d9-73b2-4703-88a3-3d730fa1e6f9","username":"JULIAN8","display_name":"JULIAN8","is_online":false,"stats":{"total_playtime":3066,"kills":6,"deaths":12,"blocks_broken":2428,"blocks_placed":682,"level":5,"distance_traveled":671526.51,"items_crafted":22,"mobs_killed":21,"food_eaten":5}},{"uuid":"0204360d-1e86-48f7-94ab-8ebba4037c22","username":"Xerayez","display_name":"Xerayez","is_online":true,"stats":{"total_playtime":1359,"kills":0,"deaths":23,"blocks_broken":1943,"blocks_placed":148,"level":0,"distance_traveled":118310.18,"items_crafted":0,"mobs_killed":2,"food_eaten":18}},{"uuid":"d723e90c-6cd4-4139-a00d-6dae9187126c","username":"KingThomas0318","display_name":"KingThomas0318","is_online":true,"stats":{"total_playtime":3893,"kills":9,"deaths":15,"blocks_broken":2626,"blocks_placed":382,"level":1,"distance_traveled":448202.71,"items_crafted":2,"mobs_killed":19,"food_eaten":12}},{"uuid":"03ae8e71-111f-4fe3-a7d0-401a7439c95e","username":"Gravephonk","display_name":"Gravephonk","is_online":false,"stats":{"total_playtime":123,"kills":7,"deaths":5,"blocks_broken":1,"blocks_placed":0,"level":3,"distance_traveled":15180.86,"items_crafted":0,"mobs_killed":0,"food_eaten":0}},{"uuid":"b8493bbf-7643-42a4-8fce-dae81464375c","username":"Ahmad34567y","display_name":"Ahmad34567y","is_online":false,"stats":{"total_playtime":183,"kills":0,"deaths":0,"blocks_broken":373,"blocks_placed":127,"level":25,"distance_traveled":107019.75,"items_crafted":17,"mobs_killed":27,"food_eaten":28}},{"uuid":"ebf7a1c4-f47e-4453-9897-4a60031c1e41","username":"Verdanting","display_name":"Verdanting","is_online":false,"stats":{"total_playtime":4246,"kills":17,"deaths":6,"blocks_broken":2366,"blocks_placed":320,"level":11,"distance_traveled":412626.15,"items_crafted":0,"mobs_killed":0,"food_eaten":0}},{"uuid":"3479efe6-23ca-4f7d-b1f5-d861e9ce81a4","username":"Pinkbearguy","display_name":"Pinkbearguy","is_online":false,"stats":{"total_playtime":1817,"kills":1,"deaths":9,"blocks_broken":1694,"blocks_placed":323,"level":39,"distance_traveled":227219.87,"items_crafted":11,"mobs_killed":36,"food_eaten":50}},{"uuid":"b91fe2e5-405a-4f90-91fc-610243107689","username":"_Quaxel","display_name":"_Quaxel","is_online":false,"stats":{"total_playtime":2650,"kills":10,"deaths":39,"blocks_broken":3985,"blocks_placed":1271,"level":1,"distance_traveled":274395.27,"items_crafted":9,"mobs_killed":34,"food_eaten":14}},{"uuid":"6066664e-f97c-4d60-be22-f37c67efc9d2","username":"babushka_v","display_name":"babushka_v","is_online":true,"stats":{"total_playtime":4317,"kills":13,"deaths":28,"blocks_broken":7246,"blocks_placed":549,"level":40,"distance_traveled":306165.40,"items_crafted":0,"mobs_killed":1,"food_eaten":3}},{"uuid":"2ff56bc1-76e1-45cd-a2c0-10d6bfeb2edd","username":"GigglingObsidian","display_name":"GigglingObsidian","is_online":true,"stats":{"total_playtime":4137,"kills":49,"deaths":3,"blocks_broken":8145,"blocks_placed":2625,"level":51,"distance_traveled":355010.98,"items_crafted":0,"mobs_killed":0,"food_eaten":1}},{"uuid":"2028c9a8-07e1-42bc-981d-4b8c471f724f","username":"Cursed_Diablo","display_name":"Cursed_Diablo","is_online":false,"stats":{"total_playtime":935,"kills":2,"deaths":3,"blocks_broken":0,"blocks_placed":299,"level":22,"distance_traveled":42179.52,"items_crafted":0,"mobs_killed":0,"food_eaten":0}},{"uuid":"8e0ae085-bf25-4108-a610-5c7976624236","username":"TheSizlrYT","display_name":"TheSizlrYT","is_online":true,"stats":{"total_playtime":16,"kills":0,"deaths":6,"blocks_broken":36,"blocks_placed":3,"level":0,"distance_traveled":2404.80,"items_crafted":0,"mobs_killed":0,"food_eaten":0}}]}