{"last_updated":1771761192635,"server":"FrostedSMP","players":[{"uuid":"f132d52b-60d1-4f49-948a-6aba033963a8","username":"drift129","display_name":"drift129","is_online":false,"stats":{"total_playtime":3539,"kills":4,"deaths":22,"blocks_broken":1016,"blocks_placed":549,"level":0,"distance_traveled":266041.71,"items_crafted":0,"mobs_killed":0,"food_eaten":10}},{"uuid":"44ce9ead-1713-4c7d-8253-fbc5178e2e79","username":"lunrdrift","display_name":"lunrdrift","is_online":false,"stats":{"total_playtime":1548,"kills":0,"deaths":4,"blocks_broken":287,"blocks_placed":245,"level":23,"distance_traveled":119103.51,"items_crafted":0,"mobs_killed":0,"food_eaten":2}}]}